---
layout: post
category: itstack-demo-jvm
title: ç”¨Javaå®ç°JVMç¬¬å…«ç« ã€Šæ•°ç»„å’Œå­—ç¬¦ä¸²ã€‹
tagline: by ä»˜æ”¿å§”
tag: [jvm,itstack-demo-jvm]
---

# ç”¨Javaå®ç°JVMç¬¬å…«ç« ã€Šæ•°ç»„å’Œå­—ç¬¦ä¸²ã€‹

ä½œè€…ï¼šå°å‚…å“¥
<br/>åšå®¢ï¼š[https://bugstack.cn](https://bugstack.cn)

> æ²‰æ·€ã€åˆ†äº«ã€æˆé•¿ï¼Œè®©è‡ªå·±å’Œä»–äººéƒ½èƒ½æœ‰æ‰€æ”¶è·ï¼ğŸ˜„

## æ¡ˆä¾‹ä»‹ç»
æœ¬ç« ä¸»è¦ä»‹ç»å¦‚ä½•å®ç°è®©è™šæ‹Ÿæœºå¤„ç†æ•°ç»„å’Œå­—ç¬¦ä¸²ï¼Œåœ¨è™šæ‹ŸæœºåŠŸèƒ½å¢å¼ºåï¼Œæˆ‘ä»¬å¯ä»¥æ‰§è¡Œæ•°ç»„ç±»å‹è®¡ç®—å’Œè¾“å‡ºå­—ç¬¦ä¸²ã€‚æœ¬ç« éœ€è¦æ–°å¢å®ç°æ•°ç»„æŒ‡ä»¤ï¼›`newarray`ã€`anewarray`ã€`arraylength`ã€`<t>aload`ã€`<t>astore`ã€`multianewarray`ã€`ldc`ï¼ŒåŒæ—¶éœ€è¦éœ€è¦å¼€å‘å­—ç¬¦ä¸²æ± æ–¹æ³•ç­‰ã€‚

>æ•°ç»„åœ¨Javaè™šæ‹Ÿæœºä¸­æ˜¯ç»™æ¯”è¾ƒç‰¹æ®Šçš„æ¦‚å¿µï¼Œä¸»è¦æœ‰ä»¥ä¸‹åŸå› ï¼›

- é¦–å…ˆï¼Œæ•°ç»„ç±»å’Œæ™®é€šçš„ç±»æ˜¯ä¸åŒçš„ã€‚æ™®é€šçš„ç±»ä»classæ–‡ä»¶ä¸­åŠ è½½ï¼Œä½†æ˜¯æ•°ç»„ç±»ç”±Javaè™šæ‹Ÿæœºåœ¨è¿è¡Œæ—¶ç”Ÿæˆã€‚æ•°ç»„çš„ç±»åæ˜¯å·¦æ‹¬å·`([)+`æ•°ç»„å…ƒç´ çš„ç±»å‹æè¿°ç¬¦ï¼›æ•°ç»„çš„ç±»å‹æè¿°ç¬¦å°±æ˜¯ç±»åæœ¬èº«ã€‚ä¾‹å¦‚ï¼Œint[]çš„ç±»åæ˜¯`[Iï¼Œint[][]`çš„ç±»åæ˜¯`[[Iï¼ŒObject[]`çš„ç±»åæ˜¯`[Ljava/lang/Object;ï¼Œ`String[][]çš„ç±»åæ˜¯`[[java/lang/String;ï¼Œ`ç­‰ç­‰ã€‚
- å…¶æ¬¡ï¼Œåˆ›å»ºæ•°ç»„çš„æ–¹å¼å’Œåˆ›å»ºæ™®é€šå¯¹è±¡çš„æ–¹å¼ä¸åŒã€‚æ™®é€šå¯¹è±¡newæŒ‡ä»¤åˆ›å»ºï¼Œç„¶åç”±æ„é€ å‡½æ•°åˆå§‹åŒ–ã€‚åŸºæœ¬ç±»å‹æ•°ç»„ç”±`newarray`æŒ‡ä»¤åˆ›å»ºï¼›å¼•ç”¨ç±»å‹æ•°ç»„ç”±anewarrayæŒ‡ä»¤åˆ›å»ºï¼›å¦å¤–è¿˜æœ‰ä¸€ä¸ªä¸“é—¨çš„mulitianewarrayæŒ‡ä»¤ç”¨äºåˆ›å»ºå¤šç»´æ•°ç»„ã€‚
- æœ€åï¼Œå¾ˆæ˜¾ç„¶ï¼Œæ•°ç»„å’Œæ™®é€šå¯¹è±¡å­˜åœ¨çš„æ•°æ®ä¹Ÿæ˜¯ä¸åŒçš„ã€‚æ™®é€šå¯¹è±¡ä¸­å­˜æ”¾çš„æ˜¯å®ä¾‹å˜é‡ï¼Œé€šè¿‡`putfield`å’Œ`getfield`æŒ‡ä»¤å­˜å–ã€‚æ•°ç»„å¯¹è±¡ä¸­å­˜æ”¾çš„åˆ™æ˜¯æ•°ç»„å…ƒç´ ï¼Œé€šè¿‡`<t>aload`å’Œ`<t>astore`ç³»åˆ—æŒ‡ä»¤æŒ‰ç´¢å¼•å­˜å–ã€‚å…¶ä¸­`<t>`å¯ä»¥æ˜¯aã€bã€cã€dã€fã€iã€læˆ–è€…sï¼Œåˆ†åˆ«ç”¨äºå­˜å–å¼•ç”¨ã€byteã€charã€doubleã€floatã€intã€longæˆ–è€…shoreç±»å‹çš„æ•°ç»„ã€‚å¦å¤–ï¼Œè¿˜æœ‰ä¸€ä¸ªarraylengthæŒ‡ä»¤ï¼Œç”¨äºè·å–æ•°ç»„é•¿åº¦ã€‚

## ç¯å¢ƒå‡†å¤‡
1. jdk 1.8.0
2. IntelliJ IDEA Community Edition 2018.3.1 x64

## é…ç½®ä¿¡æ¯
1. è°ƒè¯•é…ç½®
    1. é…ç½®ä½ç½®ï¼š`Run/Debug Configurations -> program arguments`
    2. é…ç½®å†…å®¹ï¼ˆæ‰§è¡Œæ•°ç»„è®¡ç®—ï¼‰ï¼š`-Xjre "C:\Program Files\Java\jdk1.8.0_161\jre" E:\itstack\git\istack-demo\itstack-demo-jvm\itstack-demo-jvm-08\target\test-classes\org\itstack\demo\test\BubbleSortTest`
    3. é…ç½®å†…å®¹ï¼ˆå­—ç¬¦ä¸²çš„è¾“å‡ºï¼‰ï¼š`-Xjre "C:\Program Files\Java\jdk1.8.0_161\jre" E:\itstack\git\istack-demo\itstack-demo-jvm\itstack-demo-jvm-08\target\test-classes\org\itstack\demo\test\HelloWorld -verbose true -args` ä½ å¥½ï¼Œjavaç‰ˆè™šæ‹Ÿæœºv1.0ï¼Œæ¬¢è¿ä½ çš„åˆ°æ¥ã€‚

## ä»£ç ç¤ºä¾‹
```java
itstack-demo-jvm-08
â”œâ”€â”€ pom.xml
â””â”€â”€ src
    â””â”€â”€ main
    â”‚    â””â”€â”€ java
    â”‚        â””â”€â”€ org.itstack.demo.jvm
    â”‚             â”œâ”€â”€ classfile
    â”‚             â”‚   â”œâ”€â”€ attributes   {BootstrapMethods/Code/ConstantValue...}
    â”‚             â”‚   â”œâ”€â”€ constantpool {CONSTANT_TAG_CLASS/CONSTANT_TAG_FIELDREF/CONSTANT_TAG_METHODREF...}
    â”‚             â”‚   â”œâ”€â”€ ClassFile.java
    â”‚             â”‚   â”œâ”€â”€ ClassReader.java
    â”‚             â”‚   â””â”€â”€ MemberInfo.java   
    â”‚             â”œâ”€â”€ classpath
    â”‚             â”‚   â”œâ”€â”€ impl
    â”‚             â”‚   â”‚   â”œâ”€â”€ CompositeEntry.java
    â”‚             â”‚   â”‚   â”œâ”€â”€ DirEntry.java 
    â”‚             â”‚   â”‚   â”œâ”€â”€ WildcardEntry.java 
    â”‚             â”‚   â”‚   â””â”€â”€ ZipEntry.java    
    â”‚             â”‚   â”œâ”€â”€ Classpath.java
    â”‚             â”‚   â””â”€â”€ Entry.java   
    â”‚             â”œâ”€â”€ classpath
    â”‚             â”‚   â”œâ”€â”€ base
    â”‚             â”‚   â”‚   â”œâ”€â”€ BytecodeReader.java
    â”‚             â”‚   â”‚   â”œâ”€â”€ ClassInitLogic.java
    â”‚             â”‚   â”‚   â”œâ”€â”€ Instruction.java
    â”‚             â”‚   â”‚   â”œâ”€â”€ InstructionBranch.java
    â”‚             â”‚   â”‚   â”œâ”€â”€ InstructionIndex8.java
    â”‚             â”‚   â”‚   â”œâ”€â”€ InstructionIndex16.java
    â”‚             â”‚   â”‚   â”œâ”€â”€ InstructionNoOperands.java	
    â”‚             â”‚   â”‚   â””â”€â”€ MethodInvokeLogic.java
    â”‚             â”‚   â”œâ”€â”€ comparisons
    â”‚             â”‚   â”œâ”€â”€ constants
    â”‚             â”‚   â”œâ”€â”€ control
    â”‚             â”‚   â”œâ”€â”€ conversions
    â”‚             â”‚   â”œâ”€â”€ extended
    â”‚             â”‚   â”œâ”€â”€ loads
    â”‚             â”‚   â”œâ”€â”€ math
    â”‚             â”‚   â”œâ”€â”€ references
    â”‚             â”‚   â”‚   â”œâ”€â”€ ANEW_ARRAY.java
    â”‚             â”‚   â”‚   â”œâ”€â”€ ARRAY_LENGTH.java
    â”‚             â”‚   â”‚   â”œâ”€â”€ CHECK_CAST.java
    â”‚             â”‚   â”‚   â”œâ”€â”€ GET_FIELD.java
    â”‚             â”‚   â”‚   â”œâ”€â”€ GET_STATIC.java
    â”‚             â”‚   â”‚   â”œâ”€â”€ INSTANCE_OF.java
    â”‚             â”‚   â”‚   â”œâ”€â”€ INVOKE_INTERFACE.java
    â”‚             â”‚   â”‚   â”œâ”€â”€ INVOKE_SPECIAL.java
    â”‚             â”‚   â”‚   â”œâ”€â”€ INVOKE_STATIC.java
    â”‚             â”‚   â”‚   â”œâ”€â”€ INVOKE_VIRTUAL.java
    â”‚             â”‚   â”‚   â”œâ”€â”€ MULTI_ANEW_ARRAY.java
    â”‚             â”‚   â”‚   â”œâ”€â”€ NEW.java
    â”‚             â”‚   â”‚   â”œâ”€â”€ NEW_ARRAY.java
    â”‚             â”‚   â”‚   â”œâ”€â”€ PUT_FIELD.java
    â”‚             â”‚   â”‚   â””â”€â”€ PUT_STATIC.java
    â”‚             â”‚   â”œâ”€â”€ stack
    â”‚             â”‚   â”œâ”€â”€ store
    â”‚             â”‚   â”‚   â””â”€â”€ xastore
    â”‚             â”‚   â”‚       â”œâ”€â”€ AASTORE.java	
    â”‚             â”‚   â”‚       â”œâ”€â”€ BASTORE.java	
    â”‚             â”‚   â”‚       â”œâ”€â”€ CASTORE.java	
    â”‚             â”‚   â”‚       â”œâ”€â”€ DASTORE.java
    â”‚             â”‚   â”‚       â”œâ”€â”€ FASTORE.java
    â”‚             â”‚   â”‚       â”œâ”€â”€ IASTORE.java
    â”‚             â”‚   â”‚       â”œâ”€â”€ LASTORE.java	
    â”‚             â”‚   â”‚       â””â”€â”€ SASTORE.java		
    â”‚             â”‚   â””â”€â”€ Factory   
    â”‚             â”œâ”€â”€ rtda
    â”‚             â”‚   â”œâ”€â”€ heap
    â”‚             â”‚   â”‚   â”œâ”€â”€ constantpool
    â”‚             â”‚   â”‚   â”œâ”€â”€ methodarea
    â”‚             â”‚   â”‚   â”‚   â”œâ”€â”€ Class.java    
    â”‚             â”‚   â”‚   â”‚   â”œâ”€â”€ ClassMember.java  
    â”‚             â”‚   â”‚   â”‚   â”œâ”€â”€ Field.java    
    â”‚             â”‚   â”‚   â”‚   â”œâ”€â”€ Method.java 
    â”‚             â”‚   â”‚   â”‚   â”œâ”€â”€ MethodDescriptor.java 
    â”‚             â”‚   â”‚   â”‚   â”œâ”€â”€ MethodDescriptorParser.java 
    â”‚             â”‚   â”‚   â”‚   â”œâ”€â”€ MethodLookup.java 	
    â”‚             â”‚   â”‚   â”‚   â”œâ”€â”€ Object.java   
    â”‚             â”‚   â”‚   â”‚   â”œâ”€â”€ Slots.java   
    â”‚             â”‚   â”‚   â”‚   â””â”€â”€ StringPool.java	
    â”‚             â”‚   â”‚   â””â”€â”€ ClassLoader.java  
    â”‚             â”‚   â”œâ”€â”€ Frame.java
    â”‚             â”‚   â”œâ”€â”€ JvmStack.java
    â”‚             â”‚   â”œâ”€â”€ LocalVars.java
    â”‚             â”‚   â”œâ”€â”€ OperandStack.java
    â”‚             â”‚   â”œâ”€â”€ Slot.java 
    â”‚             â”‚   â””â”€â”€ Thread.java
    â”‚             â”œâ”€â”€ Cmd.java
    â”‚             â”œâ”€â”€ Interpret.java    
    â”‚             â””â”€â”€ Main.java
    â””â”€â”€ test
         â””â”€â”€ java
             â””â”€â”€ org.itstack.demo.test
			     â”œâ”€â”€ BubbleSortTest.java
                 â””â”€â”€ HelloWorld.java
```
ä»£ç ç‰‡æ®µ

>ANEW_ARRAY.java

```java
package org.itstack.demo.jvm.instructions.references;

import org.itstack.demo.jvm.instructions.base.InstructionIndex16;
import org.itstack.demo.jvm.rtda.Frame;
import org.itstack.demo.jvm.rtda.OperandStack;
import org.itstack.demo.jvm.rtda.heap.constantpool.ClassRef;
import org.itstack.demo.jvm.rtda.heap.constantpool.RunTimeConstantPool;
import org.itstack.demo.jvm.rtda.heap.methodarea.Class;
import org.itstack.demo.jvm.rtda.heap.methodarea.Object;

/**
 * http://www.itstack.org
 * create by fuzhengwei on 2019/4/29
 * create new array of reference
 */
public class ANEW_ARRAY extends InstructionIndex16 {

    @Override
    public void execute(Frame frame) {
        
        RunTimeConstantPool runTimeConstantPool = frame.method().clazz().constantPool();
        ClassRef classRef = (ClassRef) runTimeConstantPool.getConstants(this.idx);
        Class componentClass = classRef.resolvedClass();

        OperandStack stack = frame.operandStack();
        int count = stack.popInt();
        if (count < 0) {
            throw new NegativeArraySizeException();
        }

        Class arrClass = componentClass.arrayClass();
        Object arr = arrClass.newArray(count);
        stack.pushRef(arr);

    }

}
```

>ARRAY_LENGTH.java

```java
package org.itstack.demo.jvm.instructions.references;

import org.itstack.demo.jvm.instructions.base.InstructionNoOperands;
import org.itstack.demo.jvm.rtda.Frame;
import org.itstack.demo.jvm.rtda.OperandStack;
import org.itstack.demo.jvm.rtda.heap.methodarea.Object;

/**
 * http://www.itstack.org
 * create by fuzhengwei on 2019/4/29
 * get length of array
 */
public class ARRAY_LENGTH extends InstructionNoOperands {

    @Override
    public void execute(Frame frame) {

        OperandStack stack = frame.operandStack();
        Object arrRef = stack.popRef();
        if (null == arrRef){
            throw new NullPointerException();
        }

        int arrLen = arrRef.arrayLength();
        stack.pushInt(arrLen);
    }

}
```

>NEW_ARRAY.java

```java
package org.itstack.demo.jvm.instructions.references;

import org.itstack.demo.jvm.instructions.base.BytecodeReader;
import org.itstack.demo.jvm.instructions.base.Instruction;
import org.itstack.demo.jvm.rtda.Frame;
import org.itstack.demo.jvm.rtda.OperandStack;
import org.itstack.demo.jvm.rtda.heap.ClassLoader;
import org.itstack.demo.jvm.rtda.heap.methodarea.Class;
import org.itstack.demo.jvm.rtda.heap.methodarea.Object;

/**
 * http://www.itstack.org
 * create by fuzhengwei on 2019/4/29
 */
public class NEW_ARRAY implements Instruction {

    private byte atype;

    @Override
    public void fetchOperands(BytecodeReader reader) {
        this.atype = reader.readByte();
    }

    @Override
    public void execute(Frame frame) {
        OperandStack stack = frame.operandStack();
        int count = stack.popInt();
        if (count < 0) {
            throw new NegativeArraySizeException();
        }

        ClassLoader classLoader = frame.method().clazz().loader();
        Class arrClass = getPrimitiveArrayClass(classLoader, this.atype);
        Object arr = arrClass.newArray(count);
        stack.pushRef(arr);

    }

    private Class getPrimitiveArrayClass(ClassLoader loader, byte atype){
        switch (atype) {
            case ArrayType.AT_BOOLEAN:
                return loader.loadClass("[Z");
            case ArrayType.AT_BYTE:
                return loader.loadClass("[B");
            case ArrayType.AT_CHAR:
                return loader.loadClass("[C");
            case ArrayType.AT_SHORT:
                return loader.loadClass("[S");
            case ArrayType.AT_INT:
                return loader.loadClass("[I");
            case ArrayType.AT_LONG:
                return loader.loadClass("[J");
            case ArrayType.AT_FLOAT:
                return loader.loadClass("[F");
            case ArrayType.AT_DOUBLE:
                return loader.loadClass("[D");
            default:
                throw new RuntimeException("Invalid atype!");
        }
    }

    static class ArrayType {
        static final byte AT_BOOLEAN = 4;
        static final byte AT_CHAR = 5;
        static final byte AT_FLOAT = 6;
        static final byte AT_DOUBLE = 7;
        static final byte AT_BYTE = 8;
        static final byte AT_SHORT = 9;
        static final byte AT_INT = 10;
        static final byte AT_LONG = 11;
    }

}
```

>IASTORE.java

```java
package org.itstack.demo.jvm.instructions.stores.xastore;

import org.itstack.demo.jvm.instructions.base.InstructionNoOperands;
import org.itstack.demo.jvm.rtda.Frame;
import org.itstack.demo.jvm.rtda.OperandStack;
import org.itstack.demo.jvm.rtda.heap.methodarea.Object;

/**
 * http://www.itstack.org
 * create by fuzhengwei on 2019/4/29
 */
public class IASTORE extends InstructionNoOperands {

    @Override
    public void execute(Frame frame) {
        OperandStack stack = frame.operandStack();
        int val = stack.popInt();
        int idx = stack.popInt();
        Object arrRef = stack.popRef();

        checkNotNull(arrRef);
        int[] ints = arrRef.ints();
        checkIndex(ints.length, idx);
        ints[idx] = val;

    }

}
```

>StringPool.java

```java
package org.itstack.demo.jvm.rtda.heap.methodarea;

import org.itstack.demo.jvm.rtda.heap.ClassLoader;

import java.util.HashMap;
import java.util.Map;

/**
 * http://www.itstack.org
 * create by fuzhengwei on 2019/4/29
 */
public class StringPool {

    private static Map<String, Object> internedStrs = new HashMap<>();

    public static Object jString(ClassLoader loader, String goStr) {
        Object internedStr = internedStrs.get(goStr);
        if (null != internedStr) return internedStr;

        char[] chars = goStr.toCharArray();
        Object jChars = new Object(loader.loadClass("[C"), chars);
        
        Object jStr = loader.loadClass("java/lang/String").newObject();
        jStr.setRefVal("value", "[C", jChars);

        internedStrs.put(goStr, jStr);
        return jStr;
    }

    public static String goString(Object jStr) {
        Object charArr = jStr.getRefVar("value", "[C");
        return new String(charArr.chars());
    }

}
```

>Interpret.java

```java
package org.itstack.demo.jvm;

import com.alibaba.fastjson.JSON;
import org.itstack.demo.jvm.instructions.Factory;
import org.itstack.demo.jvm.instructions.base.BytecodeReader;
import org.itstack.demo.jvm.instructions.base.Instruction;
import org.itstack.demo.jvm.rtda.Frame;
import org.itstack.demo.jvm.rtda.Thread;
import org.itstack.demo.jvm.rtda.heap.ClassLoader;
import org.itstack.demo.jvm.rtda.heap.methodarea.*;
import org.itstack.demo.jvm.rtda.heap.methodarea.Class;
import org.itstack.demo.jvm.rtda.heap.methodarea.Object;


//æŒ‡ä»¤é›†è§£é‡Šå™¨
class Interpret {

    Interpret(Method method, boolean logInst, String args) {
        Thread thread = new Thread();
        Frame frame = thread.newFrame(method);
        thread.pushFrame(frame);

        if (null != args){
            Object jArgs = createArgsArray(method.clazz().loader(), args.split(" "));
            frame.localVars().setRef(0, jArgs);
        }

        loop(thread, logInst);
    }

    private Object createArgsArray(ClassLoader loader, String[] args) {
        Class stringClass = loader.loadClass("java/lang/String");
        Object argsArr = stringClass.arrayClass().newArray(args.length);
        Object[] jArgs = argsArr.refs();
        for (int i = 0; i < jArgs.length; i++) {
            jArgs[i] = StringPool.jString(loader, args[i]);
        }
        return argsArr;
    }

    private void loop(Thread thread, boolean logInst) {
        BytecodeReader reader = new BytecodeReader();
        while (true) {
            Frame frame = thread.currentFrame();
            int pc = frame.nextPC();
            thread.setPC(pc);

            reader.reset(frame.method().code, pc);
            byte opcode = reader.readByte();
            Instruction inst = Factory.newInstruction(opcode);
            if (null == inst) {
                System.out.println("Unsupported opcode " + byteToHexString(new byte[]{opcode}));
                break;
            }
            inst.fetchOperands(reader);
            frame.setNextPC(reader.pc());

            if (logInst) {
                logInstruction(frame, inst, opcode);
            }

            //exec
            inst.execute(frame);

            if (thread.isStackEmpty()) {
                break;
            }
        }
    }

    private static void logInstruction(Frame frame, Instruction inst, byte opcode) {
        Method method = frame.method();
        String className = method.clazz().name();
        String methodName = method.name();
        String outStr = (className + "." + methodName + "() \t") +
                "å¯„å­˜å™¨(æŒ‡ä»¤)ï¼š" + byteToHexString(new byte[]{opcode}) + " -> " + inst.getClass().getSimpleName() + " => å±€éƒ¨å˜é‡è¡¨ï¼š" + JSON.toJSONString(frame.operandStack().getSlots()) + " æ“ä½œæ•°æ ˆï¼š" + JSON.toJSONString(frame.operandStack().getSlots());
        System.out.println(outStr);
    }

    private static String byteToHexString(byte[] codes) {
        StringBuilder sb = new StringBuilder();
        sb.append("0x");
        for (byte b : codes) {
            int value = b & 0xFF;
            String strHex = Integer.toHexString(value);
            if (strHex.length() < 2) {
                strHex = "0" + strHex;
            }
            sb.append(strHex);
        }
        return sb.toString();
    }

}
```

>BubbleSortTest.java

```java
package org.itstack.demo.test;

/**
 * -Xjre "C:\Program Files\Java\jdk1.8.0_161\jre" E:\itstack\git\istack-demo\itstack-demo-jvm\itstack-demo-jvm-08\target\test-classes\org\itstack\demo\test\BubbleSortTest -verbose true
 */
public class BubbleSortTest {
    
    public static void main(String[] args) {
        int[] arr = {
            22, 84, 77, 11, 95,  9, 78, 56, 
            36, 97, 65, 36, 10, 24 ,92, 48
        };

        //printArray(arr);
        bubbleSort(arr);
        //System.out.println(123456789);
        printArray(arr);
    }
    
    private static void bubbleSort(int[] arr) {
        boolean swapped = true;
        int j = 0;
        int tmp;
        while (swapped) {
            swapped = false;
            j++;
            for (int i = 0; i < arr.length - j; i++) {
                if (arr[i] > arr[i + 1]) {
                    tmp = arr[i];
                    arr[i] = arr[i + 1];
                    arr[i + 1] = tmp;
                    swapped = true;
                }
            }
        }
    }
    
    private static void printArray(int[] arr) {
        for (int i : arr) {
            System.out.println(i);
        }
    }
    
}
```

>HelloWorld.java

```java
package org.itstack.demo.test;

/**
 * -Xjre "C:\Program Files\Java\jdk1.8.0_161\jre" E:\itstack\git\istack-demo\itstack-demo-jvm\itstack-demo-jvm-08\target\test-classes\org\itstack\demo\test\HelloWorld -verbose true -args ä½ å¥½ï¼Œjavaç‰ˆè™šæ‹Ÿæœºv1.0ï¼Œæ¬¢è¿ä½ çš„åˆ°æ¥ã€‚
 */
public class HelloWorld {

    public static void main(String[] args) {
        for (String str : args) {
            System.out.println(str);
        }
    }

}
```

**æµ‹è¯•ç»“æœä¸€ï¼›æ‰§è¡Œæ•°ç»„**
```java
-Xjre "C:\Program Files\Java\jdk1.8.0_161\jre" E:\itstack\git\istack-demo\itstack-demo-jvm\itstack-demo-jvm-08\target\test-classes\org\itstack\demo\test\BubbleSortTest -verbose true
org/itstack/demo/test/BubbleSortTest.main() 	å¯„å­˜å™¨(æŒ‡ä»¤)ï¼š0x10 -> BIPUSH => å±€éƒ¨å˜é‡è¡¨ï¼š[{"num":0},{"num":0},{"num":0},{"num":0}] æ“ä½œæ•°æ ˆï¼š[{"num":0},{"num":0},{"num":0},{"num":0}]
org/itstack/demo/test/BubbleSortTest.main() 	å¯„å­˜å™¨(æŒ‡ä»¤)ï¼š0xbc -> NEW_ARRAY => å±€éƒ¨å˜é‡è¡¨ï¼š[{"num":16},{"num":0},{"num":0},{"num":0}] æ“ä½œæ•°æ ˆï¼š[{"num":16},{"num":0},{"num":0},{"num":0}]
org/itstack/demo/test/BubbleSortTest.main() 	å¯„å­˜å™¨(æŒ‡ä»¤)ï¼š0x59 -> DUP => å±€éƒ¨å˜é‡è¡¨ï¼š[{"num":16,"ref":{}},{"num":0},{"num":0},{"num":0}] æ“ä½œæ•°æ ˆï¼š[{"num":16,"ref":{}},{"num":0},{"num":0},{"num":0}]
org/itstack/demo/test/BubbleSortTest.main() 	å¯„å­˜å™¨(æŒ‡ä»¤)ï¼š0x03 -> ICONST_0 => å±€éƒ¨å˜é‡è¡¨ï¼š[{"num":16,"ref":{}},{"num":16,"ref":{"$ref":"$[0].ref"}},{"num":0},{"num":0}] æ“ä½œæ•°æ ˆï¼š[{"num":16,"ref":{}},{"num":16,"ref":{"$ref":"$[0].ref"}},{"num":0},{"num":0}]
org/itstack/demo/test/BubbleSortTest.main() 	å¯„å­˜å™¨(æŒ‡ä»¤)ï¼š0x10 -> BIPUSH => å±€éƒ¨å˜é‡è¡¨ï¼š[{"num":16,"ref":{}},{"num":16,"ref":{"$ref":"$[0].ref"}},{"num":0},{"num":0}] æ“ä½œæ•°æ ˆï¼š[{"num":16,"ref":{}},{"num":16,"ref":{"$ref":"$[0].ref"}},{"num":0},{"num":0}]
org/itstack/demo/test/BubbleSortTest.main() 	å¯„å­˜å™¨(æŒ‡ä»¤)ï¼š0x4f -> IASTORE => å±€éƒ¨å˜é‡è¡¨ï¼š[{"num":16,"ref":{}},{"num":16,"ref":{"$ref":"$[0].ref"}},{"num":0},{"num":22}] æ“ä½œæ•°æ ˆï¼š[{"num":16,"ref":{}},{"num":16,"ref":{"$ref":"$[0].ref"}},{"num":0},{"num":22}]
org/itstack/demo/test/BubbleSortTest.main() 	å¯„å­˜å™¨(æŒ‡ä»¤)ï¼š0x59 -> DUP => å±€éƒ¨å˜é‡è¡¨ï¼š[{"num":16,"ref":{}},{"num":16},{"num":0},{"num":22}] æ“ä½œæ•°æ ˆï¼š[{"num":16,"ref":{}},{"num":16},{"num":0},{"num":22}]
org/itstack/demo/test/BubbleSortTest.main() 	å¯„å­˜å™¨(æŒ‡ä»¤)ï¼š0x04 -> ICONST_1 => å±€éƒ¨å˜é‡è¡¨ï¼š[{"num":16,"ref":{}},{"num":16,"ref":{"$ref":"$[0].ref"}},{"num":0},{"num":22}] æ“ä½œæ•°æ ˆï¼š[{"num":16,"ref":{}},{"num":16,"ref":{"$ref":"$[0].ref"}},{"num":0},{"num":22}]
org/itstack/demo/test/BubbleSortTest.main() 	å¯„å­˜å™¨(æŒ‡ä»¤)ï¼š0x10 -> BIPUSH => å±€éƒ¨å˜é‡è¡¨ï¼š[{"num":16,"ref":{}},{"num":16,"ref":{"$ref":"$[0].ref"}},{"num":1},{"num":22}] æ“ä½œæ•°æ ˆï¼š[{"num":16,"ref":{}},{"num":16,"ref":{"$ref":"$[0].ref"}},{"num":1},{"num":22}]
org/itstack/demo/test/BubbleSortTest.main() 	å¯„å­˜å™¨(æŒ‡ä»¤)ï¼š0x4f -> IASTORE => å±€éƒ¨å˜é‡è¡¨ï¼š[{"num":16,"ref":{}},{"num":16,"ref":{"$ref":"$[0].ref"}},{"num":1},{"num":84}] æ“ä½œæ•°æ ˆï¼š[{"num":16,"ref":{}},{"num":16,"ref":{"$ref":"$[0].ref"}},{"num":1},{"num":84}]
org/itstack/demo/test/BubbleSortTest.main() 	å¯„å­˜å™¨(æŒ‡ä»¤)ï¼š0x59 -> DUP => å±€éƒ¨å˜é‡è¡¨ï¼š[{"num":16,"ref":{}},{"num":16},{"num":1},{"num":84}] æ“ä½œæ•°æ ˆï¼š[{"num":16,"ref":{}},{"num":16},{"num":1},{"num":84}]
org/itstack/demo/test/BubbleSortTest.main() 	å¯„å­˜å™¨(æŒ‡ä»¤)ï¼š0x05 -> ICONST_2 => å±€éƒ¨å˜é‡è¡¨ï¼š[{"num":16,"ref":{}},{"num":16,"ref":{"$ref":"$[0].ref"}},{"num":1},{"num":84}] æ“ä½œæ•°æ ˆï¼š[{"num":16,"ref":{}},{"num":16,"ref":{"$ref":"$[0].ref"}},{"num":1},{"num":84}]
org/itstack/demo/test/BubbleSortTest.main() 	å¯„å­˜å™¨(æŒ‡ä»¤)ï¼š0x10 -> BIPUSH => å±€éƒ¨å˜é‡è¡¨ï¼š[{"num":16,"ref":{}},{"num":16,"ref":{"$ref":"$[0].ref"}},{"num":2},{"num":84}] æ“ä½œæ•°æ ˆï¼š[{"num":16,"ref":{}},{"num":16,"ref":{"$ref":"$[0].ref"}},{"num":2},{"num":84}]
org/itstack/demo/test/BubbleSortTest.main() 	å¯„å­˜å™¨(æŒ‡ä»¤)ï¼š0x4f -> IASTORE => å±€éƒ¨å˜é‡è¡¨ï¼š[{"num":16,"ref":{}},{"num":16,"ref":{"$ref":"$[0].ref"}},{"num":2},{"num":77}] æ“ä½œæ•°æ ˆï¼š[{"num":16,"ref":{}},{"num":16,"ref":{"$ref":"$[0].ref"}},{"num":2},{"num":77}]
org/itstack/demo/test/BubbleSortTest.main() 	å¯„å­˜å™¨(æŒ‡ä»¤)ï¼š0x59 -> DUP => å±€éƒ¨å˜é‡è¡¨ï¼š[{"num":16,"ref":{}},{"num":16},{"num":2},{"num":77}] æ“ä½œæ•°æ ˆï¼š[{"num":16,"ref":{}},{"num":16},{"num":2},{"num":77}]
org/itstack/demo/test/BubbleSortTest.main() 	å¯„å­˜å™¨(æŒ‡ä»¤)ï¼š0x06 -> ICONST_3 => å±€éƒ¨å˜é‡è¡¨ï¼š[{"num":16,"ref":{}},{"num":16,"ref":{"$ref":"$[0].ref"}},{"num":2},{"num":77}] æ“ä½œæ•°æ ˆï¼š[{"num":16,"ref":{}},{"num":16,"ref":{"$ref":"$[0].ref"}},{"num":2},{"num":77}]
org/itstack/demo/test/BubbleSortTest.main() 	å¯„å­˜å™¨(æŒ‡ä»¤)ï¼š0x10 -> BIPUSH => å±€éƒ¨å˜é‡è¡¨ï¼š[{"num":16,"ref":{}},{"num":16,"ref":{"$ref":"$[0].ref"}},{"num":3},{"num":77}] æ“ä½œæ•°æ ˆï¼š[{"num":16,"ref":{}},{"num":16,"ref":{"$ref":"$[0].ref"}},{"num":3},{"num":77}]
org/itstack/demo/test/BubbleSortTest.main() 	å¯„å­˜å™¨(æŒ‡ä»¤)ï¼š0x4f -> IASTORE => å±€éƒ¨å˜é‡è¡¨ï¼š[{"num":16,"ref":{}},{"num":16,"ref":{"$ref":"$[0].ref"}},{"num":3},{"num":11}] æ“ä½œæ•°æ ˆï¼š[{"num":16,"ref":{}},{"num":16,"ref":{"$ref":"$[0].ref"}},{"num":3},{"num":11}]
org/itstack/demo/test/BubbleSortTest.main() 	å¯„å­˜å™¨(æŒ‡ä»¤)ï¼š0x59 -> DUP => å±€éƒ¨å˜é‡è¡¨ï¼š[{"num":16,"ref":{}},{"num":16},{"num":3},{"num":11}] æ“ä½œæ•°æ ˆï¼š[{"num":16,"ref":{}},{"num":16},{"num":3},{"num":11}]
org/itstack/demo/test/BubbleSortTest.main() 	å¯„å­˜å™¨(æŒ‡ä»¤)ï¼š0x07 -> ICONST_4 => å±€éƒ¨å˜é‡è¡¨ï¼š[{"num":16,"ref":{}},{"num":16,"ref":{"$ref":"$[0].ref"}},{"num":3},{"num":11}] æ“ä½œæ•°æ ˆï¼š[{"num":16,"ref":{}},{"num":16,"ref":{"$ref":"$[0].ref"}},{"num":3},{"num":11}]
org/itstack/demo/test/BubbleSortTest.main() 	å¯„å­˜å™¨(æŒ‡ä»¤)ï¼š0x10 -> BIPUSH => å±€éƒ¨å˜é‡è¡¨ï¼š[{"num":16,"ref":{}},{"num":16,"ref":{"$ref":"$[0].ref"}},{"num":4},{"num":11}] æ“ä½œæ•°æ ˆï¼š[{"num":16,"ref":{}},{"num":16,"ref":{"$ref":"$[0].ref"}},{"num":4},{"num":11}]
org/itstack/demo/test/BubbleSortTest.main() 	å¯„å­˜å™¨(æŒ‡ä»¤)ï¼š0x4f -> IASTORE => å±€éƒ¨å˜é‡è¡¨ï¼š[{"num":16,"ref":{}},{"num":16,"ref":{"$ref":"$[0].ref"}},{"num":4},{"num":95}] æ“ä½œæ•°æ ˆï¼š[{"num":16,"ref":{}},{"num":16,"ref":{"$ref":"$[0].ref"}},{"num":4},{"num":95}]
org/itstack/demo/test/BubbleSortTest.main() 	å¯„å­˜å™¨(æŒ‡ä»¤)ï¼š0x59 -> DUP => å±€éƒ¨å˜é‡è¡¨ï¼š[{"num":16,"ref":{}},{"num":16},{"num":4},{"num":95}] æ“ä½œæ•°æ ˆï¼š[{"num":16,"ref":{}},{"num":16},{"num":4},{"num":95}]
org/itstack/demo/test/BubbleSortTest.main() 	å¯„å­˜å™¨(æŒ‡ä»¤)ï¼š0x08 -> ICONST_5 => å±€éƒ¨å˜é‡è¡¨ï¼š[{"num":16,"ref":{}},{"num":16,"ref":{"$ref":"$[0].ref"}},{"num":4},{"num":95}] æ“ä½œæ•°æ ˆï¼š[{"num":16,"ref":{}},{"num":16,"ref":{"$ref":"$[0].ref"}},{"num":4},{"num":95}]
org/itstack/demo/test/BubbleSortTest.main() 	å¯„å­˜å™¨(æŒ‡ä»¤)ï¼š0x10 -> BIPUSH => å±€éƒ¨å˜é‡è¡¨ï¼š[{"num":16,"ref":{}},{"num":16,"ref":{"$ref":"$[0].ref"}},{"num":5},{"num":95}] æ“ä½œæ•°æ ˆï¼š[{"num":16,"ref":{}},{"num":16,"ref":{"$ref":"$[0].ref"}},{"num":5},{"num":95}]
org/itstack/demo/test/BubbleSortTest.main() 	å¯„å­˜å™¨(æŒ‡ä»¤)ï¼š0x4f -> IASTORE => å±€éƒ¨å˜é‡è¡¨ï¼š[{"num":16,"ref":{}},{"num":16,"ref":{"$ref":"$[0].ref"}},{"num":5},{"num":9}] æ“ä½œæ•°æ ˆï¼š[{"num":16,"ref":{}},{"num":16,"ref":{"$ref":"$[0].ref"}},{"num":5},{"num":9}]
org/itstack/demo/test/BubbleSortTest.main() 	å¯„å­˜å™¨(æŒ‡ä»¤)ï¼š0x59 -> DUP => å±€éƒ¨å˜é‡è¡¨ï¼š[{"num":16,"ref":{}},{"num":16},{"num":5},{"num":9}] æ“ä½œæ•°æ ˆï¼š[{"num":16,"ref":{}},{"num":16},{"num":5},{"num":9}]
org/itstack/demo/test/BubbleSortTest.main() 	å¯„å­˜å™¨(æŒ‡ä»¤)ï¼š0x10 -> BIPUSH => å±€éƒ¨å˜é‡è¡¨ï¼š[{"num":16,"ref":{}},{"num":16,"ref":{"$ref":"$[0].ref"}},{"num":5},{"num":9}] æ“ä½œæ•°æ ˆï¼š[{"num":16,"ref":{}},{"num":16,"ref":{"$ref":"$[0].ref"}},{"num":5},{"num":9}]
org/itstack/demo/test/BubbleSortTest.main() 	å¯„å­˜å™¨(æŒ‡ä»¤)ï¼š0x10 -> BIPUSH => å±€éƒ¨å˜é‡è¡¨ï¼š[{"num":16,"ref":{}},{"num":16,"ref":{"$ref":"$[0].ref"}},{"num":6},{"num":9}] æ“ä½œæ•°æ ˆï¼š[{"num":16,"ref":{}},{"num":16,"ref":{"$ref":"$[0].ref"}},{"num":6},{"num":9}]
org/itstack/demo/test/BubbleSortTest.main() 	å¯„å­˜å™¨(æŒ‡ä»¤)ï¼š0x4f -> IASTORE => å±€éƒ¨å˜é‡è¡¨ï¼š[{"num":16,"ref":{}},{"num":16,"ref":{"$ref":"$[0].ref"}},{"num":6},{"num":78}] æ“ä½œæ•°æ ˆï¼š[{"num":16,"ref":{}},{"num":16,"ref":{"$ref":"$[0].ref"}},{"num":6},{"num":78}]
org/itstack/demo/test/BubbleSortTest.main() 	å¯„å­˜å™¨(æŒ‡ä»¤)ï¼š0x59 -> DUP => å±€éƒ¨å˜é‡è¡¨ï¼š[{"num":16,"ref":{}},{"num":16},{"num":6},{"num":78}] æ“ä½œæ•°æ ˆï¼š[{"num":16,"ref":{}},{"num":16},{"num":6},{"num":78}]
org/itstack/demo/test/BubbleSortTest.main() 	å¯„å­˜å™¨(æŒ‡ä»¤)ï¼š0x10 -> BIPUSH => å±€éƒ¨å˜é‡è¡¨ï¼š[{"num":16,"ref":{}},{"num":16,"ref":{"$ref":"$[0].ref"}},{"num":6},{"num":78}] æ“ä½œæ•°æ ˆï¼š[{"num":16,"ref":{}},{"num":16,"ref":{"$ref":"$[0].ref"}},{"num":6},{"num":78}]
org/itstack/demo/test/BubbleSortTest.main() 	å¯„å­˜å™¨(æŒ‡ä»¤)ï¼š0x10 -> BIPUSH => å±€éƒ¨å˜é‡è¡¨ï¼š[{"num":16,"ref":{}},{"num":16,"ref":{"$ref":"$[0].ref"}},{"num":7},{"num":78}] æ“ä½œæ•°æ ˆï¼š[{"num":16,"ref":{}},{"num":16,"ref":{"$ref":"$[0].ref"}},{"num":7},{"num":78}]
org/itstack/demo/test/BubbleSortTest.main() 	å¯„å­˜å™¨(æŒ‡ä»¤)ï¼š0x4f -> IASTORE => å±€éƒ¨å˜é‡è¡¨ï¼š[{"num":16,"ref":{}},{"num":16,"ref":{"$ref":"$[0].ref"}},{"num":7},{"num":56}] æ“ä½œæ•°æ ˆï¼š[{"num":16,"ref":{}},{"num":16,"ref":{"$ref":"$[0].ref"}},{"num":7},{"num":56}]
org/itstack/demo/test/BubbleSortTest.main() 	å¯„å­˜å™¨(æŒ‡ä»¤)ï¼š0x59 -> DUP => å±€éƒ¨å˜é‡è¡¨ï¼š[{"num":16,"ref":{}},{"num":16},{"num":7},{"num":56}] æ“ä½œæ•°æ ˆï¼š[{"num":16,"ref":{}},{"num":16},{"num":7},{"num":56}]
org/itstack/demo/test/BubbleSortTest.main() 	å¯„å­˜å™¨(æŒ‡ä»¤)ï¼š0x10 -> BIPUSH => å±€éƒ¨å˜é‡è¡¨ï¼š[{"num":16,"ref":{}},{"num":16,"ref":{"$ref":"$[0].ref"}},{"num":7},{"num":56}] æ“ä½œæ•°æ ˆï¼š[{"num":16,"ref":{}},{"num":16,"ref":{"$ref":"$[0].ref"}},{"num":7},{"num":56}]
org/itstack/demo/test/BubbleSortTest.main() 	å¯„å­˜å™¨(æŒ‡ä»¤)ï¼š0x10 -> BIPUSH => å±€éƒ¨å˜é‡è¡¨ï¼š[{"num":16,"ref":{}},{"num":16,"ref":{"$ref":"$[0].ref"}},{"num":8},{"num":56}] æ“ä½œæ•°æ ˆï¼š[{"num":16,"ref":{}},{"num":16,"ref":{"$ref":"$[0].ref"}},{"num":8},{"num":56}]
org/itstack/demo/test/BubbleSortTest.main() 	å¯„å­˜å™¨(æŒ‡ä»¤)ï¼š0x4f -> IASTORE => å±€éƒ¨å˜é‡è¡¨ï¼š[{"num":16,"ref":{}},{"num":16,"ref":{"$ref":"$[0].ref"}},{"num":8},{"num":36}] æ“ä½œæ•°æ ˆï¼š[{"num":16,"ref":{}},{"num":16,"ref":{"$ref":"$[0].ref"}},{"num":8},{"num":36}]
org/itstack/demo/test/BubbleSortTest.main() 	å¯„å­˜å™¨(æŒ‡ä»¤)ï¼š0x59 -> DUP => å±€éƒ¨å˜é‡è¡¨ï¼š[{"num":16,"ref":{}},{"num":16},{"num":8},{"num":36}] æ“ä½œæ•°æ ˆï¼š[{"num":16,"ref":{}},{"num":16},{"num":8},{"num":36}]
org/itstack/demo/test/BubbleSortTest.main() 	å¯„å­˜å™¨(æŒ‡ä»¤)ï¼š0x10 -> BIPUSH => å±€éƒ¨å˜é‡è¡¨ï¼š[{"num":16,"ref":{}},{"num":16,"ref":{"$ref":"$[0].ref"}},{"num":8},{"num":36}] æ“ä½œæ•°æ ˆï¼š[{"num":16,"ref":{}},{"num":16,"ref":{"$ref":"$[0].ref"}},{"num":8},{"num":36}]
org/itstack/demo/test/BubbleSortTest.main() 	å¯„å­˜å™¨(æŒ‡ä»¤)ï¼š0x10 -> BIPUSH => å±€éƒ¨å˜é‡è¡¨ï¼š[{"num":16,"ref":{}},{"num":16,"ref":{"$ref":"$[0].ref"}},{"num":9},{"num":36}] æ“ä½œæ•°æ ˆï¼š[{"num":16,"ref":{}},{"num":16,"ref":{"$ref":"$[0].ref"}},{"num":9},{"num":36}]
org/itstack/demo/test/BubbleSortTest.main() 	å¯„å­˜å™¨(æŒ‡ä»¤)ï¼š0x4f -> IASTORE => å±€éƒ¨å˜é‡è¡¨ï¼š[{"num":16,"ref":{}},{"num":16,"ref":{"$ref":"$[0].ref"}},{"num":9},{"num":97}] æ“ä½œæ•°æ ˆï¼š[{"num":16,"ref":{}},{"num":16,"ref":{"$ref":"$[0].ref"}},{"num":9},{"num":97}]
org/itstack/demo/test/BubbleSortTest.main() 	å¯„å­˜å™¨(æŒ‡ä»¤)ï¼š0x59 -> DUP => å±€éƒ¨å˜é‡è¡¨ï¼š[{"num":16,"ref":{}},{"num":16},{"num":9},{"num":97}] æ“ä½œæ•°æ ˆï¼š[{"num":16,"ref":{}},{"num":16},{"num":9},{"num":97}]
org/itstack/demo/test/BubbleSortTest.main() 	å¯„å­˜å™¨(æŒ‡ä»¤)ï¼š0x10 -> BIPUSH => å±€éƒ¨å˜é‡è¡¨ï¼š[{"num":16,"ref":{}},{"num":16,"ref":{"$ref":"$[0].ref"}},{"num":9},{"num":97}] æ“ä½œæ•°æ ˆï¼š[{"num":16,"ref":{}},{"num":16,"ref":{"$ref":"$[0].ref"}},{"num":9},{"num":97}]
org/itstack/demo/test/BubbleSortTest.main() 	å¯„å­˜å™¨(æŒ‡ä»¤)ï¼š0x10 -> BIPUSH => å±€éƒ¨å˜é‡è¡¨ï¼š[{"num":16,"ref":{}},{"num":16,"ref":{"$ref":"$[0].ref"}},{"num":10},{"num":97}] æ“ä½œæ•°æ ˆï¼š[{"num":16,"ref":{}},{"num":16,"ref":{"$ref":"$[0].ref"}},{"num":10},{"num":97}]
org/itstack/demo/test/BubbleSortTest.main() 	å¯„å­˜å™¨(æŒ‡ä»¤)ï¼š0x4f -> IASTORE => å±€éƒ¨å˜é‡è¡¨ï¼š[{"num":16,"ref":{}},{"num":16,"ref":{"$ref":"$[0].ref"}},{"num":10},{"num":65}] æ“ä½œæ•°æ ˆï¼š[{"num":16,"ref":{}},{"num":16,"ref":{"$ref":"$[0].ref"}},{"num":10},{"num":65}]
org/itstack/demo/test/BubbleSortTest.main() 	å¯„å­˜å™¨(æŒ‡ä»¤)ï¼š0x59 -> DUP => å±€éƒ¨å˜é‡è¡¨ï¼š[{"num":16,"ref":{}},{"num":16},{"num":10},{"num":65}] æ“ä½œæ•°æ ˆï¼š[{"num":16,"ref":{}},{"num":16},{"num":10},{"num":65}]
org/itstack/demo/test/BubbleSortTest.main() 	å¯„å­˜å™¨(æŒ‡ä»¤)ï¼š0x10 -> BIPUSH => å±€éƒ¨å˜é‡è¡¨ï¼š[{"num":16,"ref":{}},{"num":16,"ref":{"$ref":"$[0].ref"}},{"num":10},{"num":65}] æ“ä½œæ•°æ ˆï¼š[{"num":16,"ref":{}},{"num":16,"ref":{"$ref":"$[0].ref"}},{"num":10},{"num":65}]
org/itstack/demo/test/BubbleSortTest.main() 	å¯„å­˜å™¨(æŒ‡ä»¤)ï¼š0x10 -> BIPUSH => å±€éƒ¨å˜é‡è¡¨ï¼š[{"num":16,"ref":{}},{"num":16,"ref":{"$ref":"$[0].ref"}},{"num":11},{"num":65}] æ“ä½œæ•°æ ˆï¼š[{"num":16,"ref":{}},{"num":16,"ref":{"$ref":"$[0].ref"}},{"num":11},{"num":65}]
org/itstack/demo/test/BubbleSortTest.main() 	å¯„å­˜å™¨(æŒ‡ä»¤)ï¼š0x4f -> IASTORE => å±€éƒ¨å˜é‡è¡¨ï¼š[{"num":16,"ref":{}},{"num":16,"ref":{"$ref":"$[0].ref"}},{"num":11},{"num":36}] æ“ä½œæ•°æ ˆï¼š[{"num":16,"ref":{}},{"num":16,"ref":{"$ref":"$[0].ref"}},{"num":11},{"num":36}]
org/itstack/demo/test/BubbleSortTest.main() 	å¯„å­˜å™¨(æŒ‡ä»¤)ï¼š0x59 -> DUP => å±€éƒ¨å˜é‡è¡¨ï¼š[{"num":16,"ref":{}},{"num":16},{"num":11},{"num":36}] æ“ä½œæ•°æ ˆï¼š[{"num":16,"ref":{}},{"num":16},{"num":11},{"num":36}]
org/itstack/demo/test/BubbleSortTest.main() 	å¯„å­˜å™¨(æŒ‡ä»¤)ï¼š0x10 -> BIPUSH => å±€éƒ¨å˜é‡è¡¨ï¼š[{"num":16,"ref":{}},{"num":16,"ref":{"$ref":"$[0].ref"}},{"num":11},{"num":36}] æ“ä½œæ•°æ ˆï¼š[{"num":16,"ref":{}},{"num":16,"ref":{"$ref":"$[0].ref"}},{"num":11},{"num":36}]
org/itstack/demo/test/BubbleSortTest.main() 	å¯„å­˜å™¨(æŒ‡ä»¤)ï¼š0x10 -> BIPUSH => å±€éƒ¨å˜é‡è¡¨ï¼š[{"num":16,"ref":{}},{"num":16,"ref":{"$ref":"$[0].ref"}},{"num":12},{"num":36}] æ“ä½œæ•°æ ˆï¼š[{"num":16,"ref":{}},{"num":16,"ref":{"$ref":"$[0].ref"}},{"num":12},{"num":36}]
org/itstack/demo/test/BubbleSortTest.main() 	å¯„å­˜å™¨(æŒ‡ä»¤)ï¼š0x4f -> IASTORE => å±€éƒ¨å˜é‡è¡¨ï¼š[{"num":16,"ref":{}},{"num":16,"ref":{"$ref":"$[0].ref"}},{"num":12},{"num":10}] æ“ä½œæ•°æ ˆï¼š[{"num":16,"ref":{}},{"num":16,"ref":{"$ref":"$[0].ref"}},{"num":12},{"num":10}]
org/itstack/demo/test/BubbleSortTest.main() 	å¯„å­˜å™¨(æŒ‡ä»¤)ï¼š0x59 -> DUP => å±€éƒ¨å˜é‡è¡¨ï¼š[{"num":16,"ref":{}},{"num":16},{"num":12},{"num":10}] æ“ä½œæ•°æ ˆï¼š[{"num":16,"ref":{}},{"num":16},{"num":12},{"num":10}]
org/itstack/demo/test/BubbleSortTest.main() 	å¯„å­˜å™¨(æŒ‡ä»¤)ï¼š0x10 -> BIPUSH => å±€éƒ¨å˜é‡è¡¨ï¼š[{"num":16,"ref":{}},{"num":16,"ref":{"$ref":"$[0].ref"}},{"num":12},{"num":10}] æ“ä½œæ•°æ ˆï¼š[{"num":16,"ref":{}},{"num":16,"ref":{"$ref":"$[0].ref"}},{"num":12},{"num":10}]
org/itstack/demo/test/BubbleSortTest.main() 	å¯„å­˜å™¨(æŒ‡ä»¤)ï¼š0x10 -> BIPUSH => å±€éƒ¨å˜é‡è¡¨ï¼š[{"num":16,"ref":{}},{"num":16,"ref":{"$ref":"$[0].ref"}},{"num":13},{"num":10}] æ“ä½œæ•°æ ˆï¼š[{"num":16,"ref":{}},{"num":16,"ref":{"$ref":"$[0].ref"}},{"num":13},{"num":10}]
org/itstack/demo/test/BubbleSortTest.main() 	å¯„å­˜å™¨(æŒ‡ä»¤)ï¼š0x4f -> IASTORE => å±€éƒ¨å˜é‡è¡¨ï¼š[{"num":16,"ref":{}},{"num":16,"ref":{"$ref":"$[0].ref"}},{"num":13},{"num":24}] æ“ä½œæ•°æ ˆï¼š[{"num":16,"ref":{}},{"num":16,"ref":{"$ref":"$[0].ref"}},{"num":13},{"num":24}]
org/itstack/demo/test/BubbleSortTest.main() 	å¯„å­˜å™¨(æŒ‡ä»¤)ï¼š0x59 -> DUP => å±€éƒ¨å˜é‡è¡¨ï¼š[{"num":16,"ref":{}},{"num":16},{"num":13},{"num":24}] æ“ä½œæ•°æ ˆï¼š[{"num":16,"ref":{}},{"num":16},{"num":13},{"num":24}]
org/itstack/demo/test/BubbleSortTest.main() 	å¯„å­˜å™¨(æŒ‡ä»¤)ï¼š0x10 -> BIPUSH => å±€éƒ¨å˜é‡è¡¨ï¼š[{"num":16,"ref":{}},{"num":16,"ref":{"$ref":"$[0].ref"}},{"num":13},{"num":24}] æ“ä½œæ•°æ ˆï¼š[{"num":16,"ref":{}},{"num":16,"ref":{"$ref":"$[0].ref"}},{"num":13},{"num":24}]
org/itstack/demo/test/BubbleSortTest.main() 	å¯„å­˜å™¨(æŒ‡ä»¤)ï¼š0x10 -> BIPUSH => å±€éƒ¨å˜é‡è¡¨ï¼š[{"num":16,"ref":{}},{"num":16,"ref":{"$ref":"$[0].ref"}},{"num":14},{"num":24}] æ“ä½œæ•°æ ˆï¼š[{"num":16,"ref":{}},{"num":16,"ref":{"$ref":"$[0].ref"}},{"num":14},{"num":24}]
org/itstack/demo/test/BubbleSortTest.main() 	å¯„å­˜å™¨(æŒ‡ä»¤)ï¼š0x4f -> IASTORE => å±€éƒ¨å˜é‡è¡¨ï¼š[{"num":16,"ref":{}},{"num":16,"ref":{"$ref":"$[0].ref"}},{"num":14},{"num":92}] æ“ä½œæ•°æ ˆï¼š[{"num":16,"ref":{}},{"num":16,"ref":{"$ref":"$[0].ref"}},{"num":14},{"num":92}]
org/itstack/demo/test/BubbleSortTest.main() 	å¯„å­˜å™¨(æŒ‡ä»¤)ï¼š0x59 -> DUP => å±€éƒ¨å˜é‡è¡¨ï¼š[{"num":16,"ref":{}},{"num":16},{"num":14},{"num":92}] æ“ä½œæ•°æ ˆï¼š[{"num":16,"ref":{}},{"num":16},{"num":14},{"num":92}]
org/itstack/demo/test/BubbleSortTest.main() 	å¯„å­˜å™¨(æŒ‡ä»¤)ï¼š0x10 -> BIPUSH => å±€éƒ¨å˜é‡è¡¨ï¼š[{"num":16,"ref":{}},{"num":16,"ref":{"$ref":"$[0].ref"}},{"num":14},{"num":92}] æ“ä½œæ•°æ ˆï¼š[{"num":16,"ref":{}},{"num":16,"ref":{"$ref":"$[0].ref"}},{"num":14},{"num":92}]
org/itstack/demo/test/BubbleSortTest.main() 	å¯„å­˜å™¨(æŒ‡ä»¤)ï¼š0x10 -> BIPUSH => å±€éƒ¨å˜é‡è¡¨ï¼š[{"num":16,"ref":{}},{"num":16,"ref":{"$ref":"$[0].ref"}},{"num":15},{"num":92}] æ“ä½œæ•°æ ˆï¼š[{"num":16,"ref":{}},{"num":16,"ref":{"$ref":"$[0].ref"}},{"num":15},{"num":92}]
org/itstack/demo/test/BubbleSortTest.main() 	å¯„å­˜å™¨(æŒ‡ä»¤)ï¼š0x4f -> IASTORE => å±€éƒ¨å˜é‡è¡¨ï¼š[{"num":16,"ref":{}},{"num":16,"ref":{"$ref":"$[0].ref"}},{"num":15},{"num":48}] æ“ä½œæ•°æ ˆï¼š[{"num":16,"ref":{}},{"num":16,"ref":{"$ref":"$[0].ref"}},{"num":15},{"num":48}]
org/itstack/demo/test/BubbleSortTest.main() 	å¯„å­˜å™¨(æŒ‡ä»¤)ï¼š0x4c -> ASTORE_1 => å±€éƒ¨å˜é‡è¡¨ï¼š[{"num":16,"ref":{}},{"num":16},{"num":15},{"num":48}] æ“ä½œæ•°æ ˆï¼š[{"num":16,"ref":{}},{"num":16},{"num":15},{"num":48}]
org/itstack/demo/test/BubbleSortTest.main() 	å¯„å­˜å™¨(æŒ‡ä»¤)ï¼š0x2b -> ALOAD_1 => å±€éƒ¨å˜é‡è¡¨ï¼š[{"num":16},{"num":16},{"num":15},{"num":48}] æ“ä½œæ•°æ ˆï¼š[{"num":16},{"num":16},{"num":15},{"num":48}]
org/itstack/demo/test/BubbleSortTest.main() 	å¯„å­˜å™¨(æŒ‡ä»¤)ï¼š0xb8 -> INVOKE_STATIC => å±€éƒ¨å˜é‡è¡¨ï¼š[{"num":16,"ref":{}},{"num":16},{"num":15},{"num":48}] æ“ä½œæ•°æ ˆï¼š[{"num":16,"ref":{}},{"num":16},{"num":15},{"num":48}]
java/lang/Object.<clinit>() 	å¯„å­˜å™¨(æŒ‡ä»¤)ï¼š0xb8 -> INVOKE_STATIC => å±€éƒ¨å˜é‡è¡¨ï¼šnull æ“ä½œæ•°æ ˆï¼šnull
java/lang/Object.<clinit>() 	å¯„å­˜å™¨(æŒ‡ä»¤)ï¼š0xb1 -> RETURN => å±€éƒ¨å˜é‡è¡¨ï¼šnull æ“ä½œæ•°æ ˆï¼šnull
... ...
org/itstack/demo/test/BubbleSortTest.printArray() 	å¯„å­˜å™¨(æŒ‡ä»¤)ï¼š0xb2 -> GET_STATIC => å±€éƒ¨å˜é‡è¡¨ï¼š[{"num":9},{"num":0}] æ“ä½œæ•°æ ˆï¼š[{"num":9},{"num":0}]
org/itstack/demo/test/BubbleSortTest.printArray() 	å¯„å­˜å™¨(æŒ‡ä»¤)ï¼š0x15 -> ILOAD => å±€éƒ¨å˜é‡è¡¨ï¼š[{"num":9},{"num":0}] æ“ä½œæ•°æ ˆï¼š[{"num":9},{"num":0}]
org/itstack/demo/test/BubbleSortTest.printArray() 	å¯„å­˜å™¨(æŒ‡ä»¤)ï¼š0xb6 -> INVOKE_VIRTUAL => å±€éƒ¨å˜é‡è¡¨ï¼š[{"num":9},{"num":9}] æ“ä½œæ•°æ ˆï¼š[{"num":9},{"num":9}]
9
org/itstack/demo/test/BubbleSortTest.printArray() 	å¯„å­˜å™¨(æŒ‡ä»¤)ï¼š0x84 -> IINC => å±€éƒ¨å˜é‡è¡¨ï¼š[{"num":9},{"num":9}] æ“ä½œæ•°æ ˆï¼š[{"num":9},{"num":9}]
org/itstack/demo/test/BubbleSortTest.printArray() 	å¯„å­˜å™¨(æŒ‡ä»¤)ï¼š0xa7 -> GOTO => å±€éƒ¨å˜é‡è¡¨ï¼š[{"num":9},{"num":9}] æ“ä½œæ•°æ ˆï¼š[{"num":9},{"num":9}]
org/itstack/demo/test/BubbleSortTest.printArray() 	å¯„å­˜å™¨(æŒ‡ä»¤)ï¼š0x1d -> ILOAD_3 => å±€éƒ¨å˜é‡è¡¨ï¼š[{"num":9},{"num":9}] æ“ä½œæ•°æ ˆï¼š[{"num":9},{"num":9}]
org/itstack/demo/test/BubbleSortTest.printArray() 	å¯„å­˜å™¨(æŒ‡ä»¤)ï¼š0x1c -> ILOAD_2 => å±€éƒ¨å˜é‡è¡¨ï¼š[{"num":1},{"num":9}] æ“ä½œæ•°æ ˆï¼š[{"num":1},{"num":9}]
org/itstack/demo/test/BubbleSortTest.printArray() 	å¯„å­˜å™¨(æŒ‡ä»¤)ï¼š0xa2 -> IF_ICMPGE => å±€éƒ¨å˜é‡è¡¨ï¼š[{"num":1},{"num":16}] æ“ä½œæ•°æ ˆï¼š[{"num":1},{"num":16}]
org/itstack/demo/test/BubbleSortTest.printArray() 	å¯„å­˜å™¨(æŒ‡ä»¤)ï¼š0x2b -> ALOAD_1 => å±€éƒ¨å˜é‡è¡¨ï¼š[{"num":1},{"num":16}] æ“ä½œæ•°æ ˆï¼š[{"num":1},{"num":16}]
org/itstack/demo/test/BubbleSortTest.printArray() 	å¯„å­˜å™¨(æŒ‡ä»¤)ï¼š0x1d -> ILOAD_3 => å±€éƒ¨å˜é‡è¡¨ï¼š[{"num":1,"ref":{}},{"num":16}] æ“ä½œæ•°æ ˆï¼š[{"num":1,"ref":{}},{"num":16}]
org/itstack/demo/test/BubbleSortTest.printArray() 	å¯„å­˜å™¨(æŒ‡ä»¤)ï¼š0x2e -> IALOAD => å±€éƒ¨å˜é‡è¡¨ï¼š[{"num":1,"ref":{}},{"num":1}] æ“ä½œæ•°æ ˆï¼š[{"num":1,"ref":{}},{"num":1}]
org/itstack/demo/test/BubbleSortTest.printArray() 	å¯„å­˜å™¨(æŒ‡ä»¤)ï¼š0x36 -> ISTORE => å±€éƒ¨å˜é‡è¡¨ï¼š[{"num":10},{"num":1}] æ“ä½œæ•°æ ˆï¼š[{"num":10},{"num":1}]
org/itstack/demo/test/BubbleSortTest.printArray() 	å¯„å­˜å™¨(æŒ‡ä»¤)ï¼š0xb2 -> GET_STATIC => å±€éƒ¨å˜é‡è¡¨ï¼š[{"num":10},{"num":1}] æ“ä½œæ•°æ ˆï¼š[{"num":10},{"num":1}]
org/itstack/demo/test/BubbleSortTest.printArray() 	å¯„å­˜å™¨(æŒ‡ä»¤)ï¼š0x15 -> ILOAD => å±€éƒ¨å˜é‡è¡¨ï¼š[{"num":10},{"num":1}] æ“ä½œæ•°æ ˆï¼š[{"num":10},{"num":1}]
org/itstack/demo/test/BubbleSortTest.printArray() 	å¯„å­˜å™¨(æŒ‡ä»¤)ï¼š0xb6 -> INVOKE_VIRTUAL => å±€éƒ¨å˜é‡è¡¨ï¼š[{"num":10},{"num":10}] æ“ä½œæ•°æ ˆï¼š[{"num":10},{"num":10}]
10
11
22
24
36
36
48
56
65
77
78
84
92
95
97
org/itstack/demo/test/BubbleSortTest.printArray() 	å¯„å­˜å™¨(æŒ‡ä»¤)ï¼š0x84 -> IINC => å±€éƒ¨å˜é‡è¡¨ï¼š[{"num":97},{"num":97}] æ“ä½œæ•°æ ˆï¼š[{"num":97},{"num":97}]
org/itstack/demo/test/BubbleSortTest.printArray() 	å¯„å­˜å™¨(æŒ‡ä»¤)ï¼š0xa7 -> GOTO => å±€éƒ¨å˜é‡è¡¨ï¼š[{"num":97},{"num":97}] æ“ä½œæ•°æ ˆï¼š[{"num":97},{"num":97}]
org/itstack/demo/test/BubbleSortTest.printArray() 	å¯„å­˜å™¨(æŒ‡ä»¤)ï¼š0x1d -> ILOAD_3 => å±€éƒ¨å˜é‡è¡¨ï¼š[{"num":97},{"num":97}] æ“ä½œæ•°æ ˆï¼š[{"num":97},{"num":97}]
org/itstack/demo/test/BubbleSortTest.printArray() 	å¯„å­˜å™¨(æŒ‡ä»¤)ï¼š0x1c -> ILOAD_2 => å±€éƒ¨å˜é‡è¡¨ï¼š[{"num":16},{"num":97}] æ“ä½œæ•°æ ˆï¼š[{"num":16},{"num":97}]
org/itstack/demo/test/BubbleSortTest.printArray() 	å¯„å­˜å™¨(æŒ‡ä»¤)ï¼š0xa2 -> IF_ICMPGE => å±€éƒ¨å˜é‡è¡¨ï¼š[{"num":16},{"num":16}] æ“ä½œæ•°æ ˆï¼š[{"num":16},{"num":16}]
org/itstack/demo/test/BubbleSortTest.printArray() 	å¯„å­˜å™¨(æŒ‡ä»¤)ï¼š0xb1 -> RETURN => å±€éƒ¨å˜é‡è¡¨ï¼š[{"num":16},{"num":16}] æ“ä½œæ•°æ ˆï¼š[{"num":16},{"num":16}]
org/itstack/demo/test/BubbleSortTest.main() 	å¯„å­˜å™¨(æŒ‡ä»¤)ï¼š0xb1 -> RETURN => å±€éƒ¨å˜é‡è¡¨ï¼š[{"num":16,"ref":{}},{"num":16},{"num":15},{"num":48}] æ“ä½œæ•°æ ˆï¼š[{"num":16,"ref":{}},{"num":16},{"num":15},{"num":48}]

Process finished with exit code 0

```

## æµ‹è¯•ç»“æœäºŒï¼›è¾“å‡ºå­—ç¬¦
```java
org/itstack/demo/test/HelloWorld.main() 	å¯„å­˜å™¨(æŒ‡ä»¤)ï¼š0x2a -> ALOAD_0 => å±€éƒ¨å˜é‡è¡¨ï¼š[{"num":0},{"num":0}] æ“ä½œæ•°æ ˆï¼š[{"num":0},{"num":0}]
org/itstack/demo/test/HelloWorld.main() 	å¯„å­˜å™¨(æŒ‡ä»¤)ï¼š0x4c -> ASTORE_1 => å±€éƒ¨å˜é‡è¡¨ï¼š[{"num":0,"ref":{}},{"num":0}] æ“ä½œæ•°æ ˆï¼š[{"num":0,"ref":{}},{"num":0}]
org/itstack/demo/test/HelloWorld.main() 	å¯„å­˜å™¨(æŒ‡ä»¤)ï¼š0x2b -> ALOAD_1 => å±€éƒ¨å˜é‡è¡¨ï¼š[{"num":0},{"num":0}] æ“ä½œæ•°æ ˆï¼š[{"num":0},{"num":0}]
org/itstack/demo/test/HelloWorld.main() 	å¯„å­˜å™¨(æŒ‡ä»¤)ï¼š0xbe -> ARRAY_LENGTH => å±€éƒ¨å˜é‡è¡¨ï¼š[{"num":0,"ref":{}},{"num":0}] æ“ä½œæ•°æ ˆï¼š[{"num":0,"ref":{}},{"num":0}]
org/itstack/demo/test/HelloWorld.main() 	å¯„å­˜å™¨(æŒ‡ä»¤)ï¼š0x3d -> ISTORE_2 => å±€éƒ¨å˜é‡è¡¨ï¼š[{"num":1},{"num":0}] æ“ä½œæ•°æ ˆï¼š[{"num":1},{"num":0}]
org/itstack/demo/test/HelloWorld.main() 	å¯„å­˜å™¨(æŒ‡ä»¤)ï¼š0x03 -> ICONST_0 => å±€éƒ¨å˜é‡è¡¨ï¼š[{"num":1},{"num":0}] æ“ä½œæ•°æ ˆï¼š[{"num":1},{"num":0}]
org/itstack/demo/test/HelloWorld.main() 	å¯„å­˜å™¨(æŒ‡ä»¤)ï¼š0x3e -> ISTORE_3 => å±€éƒ¨å˜é‡è¡¨ï¼š[{"num":0},{"num":0}] æ“ä½œæ•°æ ˆï¼š[{"num":0},{"num":0}]
org/itstack/demo/test/HelloWorld.main() 	å¯„å­˜å™¨(æŒ‡ä»¤)ï¼š0x1d -> ILOAD_3 => å±€éƒ¨å˜é‡è¡¨ï¼š[{"num":0},{"num":0}] æ“ä½œæ•°æ ˆï¼š[{"num":0},{"num":0}]
org/itstack/demo/test/HelloWorld.main() 	å¯„å­˜å™¨(æŒ‡ä»¤)ï¼š0x1c -> ILOAD_2 => å±€éƒ¨å˜é‡è¡¨ï¼š[{"num":0},{"num":0}] æ“ä½œæ•°æ ˆï¼š[{"num":0},{"num":0}]
org/itstack/demo/test/HelloWorld.main() 	å¯„å­˜å™¨(æŒ‡ä»¤)ï¼š0xa2 -> IF_ICMPGE => å±€éƒ¨å˜é‡è¡¨ï¼š[{"num":0},{"num":1}] æ“ä½œæ•°æ ˆï¼š[{"num":0},{"num":1}]
org/itstack/demo/test/HelloWorld.main() 	å¯„å­˜å™¨(æŒ‡ä»¤)ï¼š0x2b -> ALOAD_1 => å±€éƒ¨å˜é‡è¡¨ï¼š[{"num":0},{"num":1}] æ“ä½œæ•°æ ˆï¼š[{"num":0},{"num":1}]
org/itstack/demo/test/HelloWorld.main() 	å¯„å­˜å™¨(æŒ‡ä»¤)ï¼š0x1d -> ILOAD_3 => å±€éƒ¨å˜é‡è¡¨ï¼š[{"num":0,"ref":{}},{"num":1}] æ“ä½œæ•°æ ˆï¼š[{"num":0,"ref":{}},{"num":1}]
org/itstack/demo/test/HelloWorld.main() 	å¯„å­˜å™¨(æŒ‡ä»¤)ï¼š0x32 -> AALOAD => å±€éƒ¨å˜é‡è¡¨ï¼š[{"num":0,"ref":{}},{"num":0}] æ“ä½œæ•°æ ˆï¼š[{"num":0,"ref":{}},{"num":0}]
org/itstack/demo/test/HelloWorld.main() 	å¯„å­˜å™¨(æŒ‡ä»¤)ï¼š0x3a -> ASTORE => å±€éƒ¨å˜é‡è¡¨ï¼š[{"num":0,"ref":{}},{"num":0}] æ“ä½œæ•°æ ˆï¼š[{"num":0,"ref":{}},{"num":0}]
org/itstack/demo/test/HelloWorld.main() 	å¯„å­˜å™¨(æŒ‡ä»¤)ï¼š0xb2 -> GET_STATIC => å±€éƒ¨å˜é‡è¡¨ï¼š[{"num":0},{"num":0}] æ“ä½œæ•°æ ˆï¼š[{"num":0},{"num":0}]
java/lang/Object.<clinit>() 	å¯„å­˜å™¨(æŒ‡ä»¤)ï¼š0xb8 -> INVOKE_STATIC => å±€éƒ¨å˜é‡è¡¨ï¼šnull æ“ä½œæ•°æ ˆï¼šnull
java/lang/Object.<clinit>() 	å¯„å­˜å™¨(æŒ‡ä»¤)ï¼š0xb1 -> RETURN => å±€éƒ¨å˜é‡è¡¨ï¼šnull æ“ä½œæ•°æ ˆï¼šnull
java/lang/System.<clinit>() 	å¯„å­˜å™¨(æŒ‡ä»¤)ï¼š0xb8 -> INVOKE_STATIC => å±€éƒ¨å˜é‡è¡¨ï¼š[{"num":0}] æ“ä½œæ•°æ ˆï¼š[{"num":0}]
java/lang/System.<clinit>() 	å¯„å­˜å™¨(æŒ‡ä»¤)ï¼š0x01 -> ACONST_NULL => å±€éƒ¨å˜é‡è¡¨ï¼š[{"num":0}] æ“ä½œæ•°æ ˆï¼š[{"num":0}]
java/lang/System.<clinit>() 	å¯„å­˜å™¨(æŒ‡ä»¤)ï¼š0xb3 -> PUT_STATIC => å±€éƒ¨å˜é‡è¡¨ï¼š[{"num":0}] æ“ä½œæ•°æ ˆï¼š[{"num":0}]
java/lang/System.<clinit>() 	å¯„å­˜å™¨(æŒ‡ä»¤)ï¼š0x01 -> ACONST_NULL => å±€éƒ¨å˜é‡è¡¨ï¼š[{"num":0}] æ“ä½œæ•°æ ˆï¼š[{"num":0}]
java/lang/System.<clinit>() 	å¯„å­˜å™¨(æŒ‡ä»¤)ï¼š0xb3 -> PUT_STATIC => å±€éƒ¨å˜é‡è¡¨ï¼š[{"num":0}] æ“ä½œæ•°æ ˆï¼š[{"num":0}]
java/lang/System.<clinit>() 	å¯„å­˜å™¨(æŒ‡ä»¤)ï¼š0x01 -> ACONST_NULL => å±€éƒ¨å˜é‡è¡¨ï¼š[{"num":0}] æ“ä½œæ•°æ ˆï¼š[{"num":0}]
java/lang/System.<clinit>() 	å¯„å­˜å™¨(æŒ‡ä»¤)ï¼š0xb3 -> PUT_STATIC => å±€éƒ¨å˜é‡è¡¨ï¼š[{"num":0}] æ“ä½œæ•°æ ˆï¼š[{"num":0}]
java/lang/System.<clinit>() 	å¯„å­˜å™¨(æŒ‡ä»¤)ï¼š0x01 -> ACONST_NULL => å±€éƒ¨å˜é‡è¡¨ï¼š[{"num":0}] æ“ä½œæ•°æ ˆï¼š[{"num":0}]
java/lang/System.<clinit>() 	å¯„å­˜å™¨(æŒ‡ä»¤)ï¼š0xb3 -> PUT_STATIC => å±€éƒ¨å˜é‡è¡¨ï¼š[{"num":0}] æ“ä½œæ•°æ ˆï¼š[{"num":0}]
java/lang/System.<clinit>() 	å¯„å­˜å™¨(æŒ‡ä»¤)ï¼š0x01 -> ACONST_NULL => å±€éƒ¨å˜é‡è¡¨ï¼š[{"num":0}] æ“ä½œæ•°æ ˆï¼š[{"num":0}]
java/lang/System.<clinit>() 	å¯„å­˜å™¨(æŒ‡ä»¤)ï¼š0xb3 -> PUT_STATIC => å±€éƒ¨å˜é‡è¡¨ï¼š[{"num":0}] æ“ä½œæ•°æ ˆï¼š[{"num":0}]
java/lang/System.<clinit>() 	å¯„å­˜å™¨(æŒ‡ä»¤)ï¼š0xb1 -> RETURN => å±€éƒ¨å˜é‡è¡¨ï¼š[{"num":0}] æ“ä½œæ•°æ ˆï¼š[{"num":0}]
org/itstack/demo/test/HelloWorld.main() 	å¯„å­˜å™¨(æŒ‡ä»¤)ï¼š0xb2 -> GET_STATIC => å±€éƒ¨å˜é‡è¡¨ï¼š[{"num":0},{"num":0}] æ“ä½œæ•°æ ˆï¼š[{"num":0},{"num":0}]
org/itstack/demo/test/HelloWorld.main() 	å¯„å­˜å™¨(æŒ‡ä»¤)ï¼š0x19 -> ALOAD => å±€éƒ¨å˜é‡è¡¨ï¼š[{"num":0},{"num":0}] æ“ä½œæ•°æ ˆï¼š[{"num":0},{"num":0}]
org/itstack/demo/test/HelloWorld.main() 	å¯„å­˜å™¨(æŒ‡ä»¤)ï¼š0xb6 -> INVOKE_VIRTUAL => å±€éƒ¨å˜é‡è¡¨ï¼š[{"num":0},{"num":0,"ref":{}}] æ“ä½œæ•°æ ˆï¼š[{"num":0},{"num":0,"ref":{}}]

ä½ å¥½ï¼Œjavaç‰ˆè™šæ‹Ÿæœºv1.0ï¼Œæ¬¢è¿ä½ çš„åˆ°æ¥ã€‚

org/itstack/demo/test/HelloWorld.main() 	å¯„å­˜å™¨(æŒ‡ä»¤)ï¼š0x84 -> IINC => å±€éƒ¨å˜é‡è¡¨ï¼š[{"num":0},{"num":0}] æ“ä½œæ•°æ ˆï¼š[{"num":0},{"num":0}]
org/itstack/demo/test/HelloWorld.main() 	å¯„å­˜å™¨(æŒ‡ä»¤)ï¼š0xa7 -> GOTO => å±€éƒ¨å˜é‡è¡¨ï¼š[{"num":0},{"num":0}] æ“ä½œæ•°æ ˆï¼š[{"num":0},{"num":0}]
org/itstack/demo/test/HelloWorld.main() 	å¯„å­˜å™¨(æŒ‡ä»¤)ï¼š0x1d -> ILOAD_3 => å±€éƒ¨å˜é‡è¡¨ï¼š[{"num":0},{"num":0}] æ“ä½œæ•°æ ˆï¼š[{"num":0},{"num":0}]
org/itstack/demo/test/HelloWorld.main() 	å¯„å­˜å™¨(æŒ‡ä»¤)ï¼š0x1c -> ILOAD_2 => å±€éƒ¨å˜é‡è¡¨ï¼š[{"num":1},{"num":0}] æ“ä½œæ•°æ ˆï¼š[{"num":1},{"num":0}]
org/itstack/demo/test/HelloWorld.main() 	å¯„å­˜å™¨(æŒ‡ä»¤)ï¼š0xa2 -> IF_ICMPGE => å±€éƒ¨å˜é‡è¡¨ï¼š[{"num":1},{"num":1}] æ“ä½œæ•°æ ˆï¼š[{"num":1},{"num":1}]
org/itstack/demo/test/HelloWorld.main() 	å¯„å­˜å™¨(æŒ‡ä»¤)ï¼š0xb1 -> RETURN => å±€éƒ¨å˜é‡è¡¨ï¼š[{"num":1},{"num":1}] æ“ä½œæ•°æ ˆï¼š[{"num":1},{"num":1}]
```

å¾®ä¿¡æœç´¢ã€Œ**bugstackè™«æ´æ ˆ**ã€å…¬ä¼—å·ï¼Œå…³æ³¨åå›å¤ã€Œ**ç”¨Javaå®ç°jvmæºç **ã€è·å–æœ¬æ–‡æºç &æ›´å¤šåŸåˆ›ä¸“é¢˜æ¡ˆä¾‹ï¼
